{
    "global": {
        "title": "anomaly-nbr-connect graph on fw-paris",
        "start": "2023-06-04T15:31:51+02:00",
        "end": "2023-06-05T15:31:51+02:00",
        "vertical-label": "Value",
        "base": 1000,
        "width": 550,
        "height": 140,
        "scaled": 1,
        "multiple_services": false
    },
    "metrics": [
        {
            "index_id": 152034,
            "metric_id": 15167,
            "metric": "connection",
            "metric_legend": "connection",
            "unit": "",
            "hidden": 0,
            "min": null,
            "max": null,
            "virtual": 0,
            "ds_data": {
                "ds_min": "1",
                "ds_max": "1",
                "ds_minmax_int": "0",
                "ds_last": "1",
                "ds_average": "1",
                "ds_total": "0",
                "ds_tickness": 1,
                "ds_color_line_mode": "1",
                "ds_color_line": "#66ff00"
            },
            "legend": "connection",
            "stack": 0,
            "warn": null,
            "warn_low": null,
            "crit": null,
            "crit_low": null,
            "ds_color_area_warn": "#ff9a13",
            "ds_color_area_crit": "#e00b3d",
            "ds_order": 0,
            "data": [
                147.31666667,
                137.68333333,
                109.71666667,
                150,
                144.2,
                120.98333333,
                144.2,
                123.8,
                140.28333333,
                132.9,
                172.86666667,
                117.63333333,
                123.28333333,
                147.23333333,
                101.86666667,
                123.25,
                145.53333333,
                150.56666667,
                153.35,
                97.6,
                147.01666667,
                123.48333333,
                179.36666667,
                147.08333333,
                130.65,
                129.21666667,
                100.8,
                143.91666667,
                155.65,
                158.13333333,
                45.416666667,
                15.566666667,
                24.616666667,
                23.083333333,
                23.566666667,
                15.383333333,
                21.616666667,
                27.133333333,
                20.166666667,
                12.516666667,
                17.266666667,
                18.216666667,
                12.516666667,
                14.133333333,
                11.083333333,
                21.75,
                21.866666667,
                18.65,
                26.616666667,
                26.65,
                15.816666667,
                22.4,
                28.133333333,
                25.866666667,
                28.133333333,
                21.166666667,
                22.916666667,
                20.083333333,
                24.483333333,
                22.866666667,
                25.133333333,
                26,
                27.566666667,
                13.9,
                15.483333333,
                13.866666667,
                16.133333333,
                20.916666667,
                15.733333333,
                25.75,
                22.733333333,
                24.916666667,
                20.516666667,
                19.783333333,
                19.216666667,
                24.483333333,
                24.433333333,
                16.95,
                25.966666667,
                14.116666667,
                11.566666667,
                15.133333333,
                18.35,
                21.35,
                23.566666667,
                15.383333333,
                23.183333333,
                16.6,
                23.4,
                13.466666667,
                24.883333333,
                29,
                20.383333333,
                13.3,
                12,
                12,
                14.35,
                17.35,
                21.916666667,
                24.566666667,
                14.033333333,
                24.316666667,
                17.816666667,
                14.216666667,
                13.216666667,
                21.616666667,
                25.566666667,
                27.566666667,
                16.25,
                20.05,
                26.7,
                22.516666667,
                26.483333333,
                25.65,
                17.166666667,
                20.483333333,
                16.516666667,
                15.783333333,
                18.35,
                21.35,
                26.7,
                22.516666667,
                26.483333333,
                22.516666667,
                19.433333333,
                19.783333333,
                17.65,
                15.433333333,
                18.133333333,
                12.733333333,
                21.183333333,
                13.816666667,
                14.133333333,
                13.433333333,
                21.616666667,
                26.35,
                20.733333333,
                25.266666667,
                27,
                27,
                26.216666667,
                27.566666667,
                17.816666667,
                11.866666667,
                17.266666667,
                20.566666667,
                26.483333333,
                26.433333333,
                15.816666667,
                24.75,
                23.3,
                14.95,
                24.75,
                23.3,
                20.433333333,
                24.7,
                28.35,
                16.466666667,
                25.533333333,
                27.433333333,
                26.216666667,
                28.35,
                16.466666667,
                16.916666667,
                12.516666667,
                11,
                11,
                17.266666667,
                20.566666667,
                24.133333333,
                23.433333333,
                22.216666667,
                27.483333333,
                19.6,
                23.266666667,
                23.433333333,
                21.433333333,
                24.133333333,
                13.25,
                24.883333333,
                14.9,
                12.566666667,
                16.133333333,
                21.7,
                23,
                19.083333333,
                16.433333333,
                17.566666667,
                14.866666667,
                17.916666667,
                19.783333333,
                16.866666667,
                19.133333333,
                24.7,
                16.6,
                11.65,
                18.833333333,
                24.133333333,
                21.866666667,
                27.266666667,
                18.816666667,
                23.833333333,
                23.65,
                18.3,
                16.216666667,
                20.7,
                25.916666667,
                15.25,
                16.7,
                14.083333333,
                134.41666667,
                133.41666667,
                103.25,
                144.5,
                158.08333333,
                153.83333333,
                129.75,
                109.5,
                142.91666667,
                117.75,
                105.58333333,
                150.75,
                145.75,
                153.83333333,
                132.75,
                154.75,
                179.91666667,
                149.83333333,
                117.08333333,
                127.16666667,
                138.33333333,
                122.75,
                149.58333333,
                145.83333333,
                116.83333333,
                108.08333333,
                118.25,
                141,
                158,
                168.83333333,
                164.25,
                145.16666667,
                158.16666667,
                129.66666667,
                98,
                97.416666667,
                92.916666667,
                89.416666667,
                128.66666667,
                116.16666667,
                93.416666667,
                117.25,
                153.16666667,
                155.58333333,
                149.5,
                115.83333333,
                103.41666667,
                129.91666667,
                118.66666667,
                130,
                144.16666667,
                112.58333333,
                94.75,
                126.33333333,
                134,
                114.08333333,
                128,
                106.25,
                116.75,
                106.25,
                115,
                123.66666667,
                93.916666667,
                131.75,
                138.83333333,
                118,
                125.58333333,
                117.58333333,
                113.83333333,
                120.33333333,
                140.66666667,
                147.58333333,
                173.33333333,
                176.33333333,
                132.66666667,
                116.83333333,
                111.66666667,
                null,
                null
            ],
            "prints": [
                [
                    "Last:111.67"
                ],
                [
                    "Min:11.00"
                ],
                [
                    "Max:179.92"
                ],
                [
                    "Average:61.85"
                ]
            ],
            "last_value": 111.67,
            "minimum_value": 11,
            "maximum_value": 179.92,
            "average_value": 61.85
        },
        {
            "index_id": 152034,
            "metric_id": 16202,
            "metric": "connection_fit",
            "metric_legend": "connection_fit",
            "unit": "",
            "hidden": 0,
            "min": null,
            "max": null,
            "virtual": 0,
            "ds_data": {
                "ds_min": "1",
                "ds_max": "1",
                "ds_minmax_int": "0",
                "ds_last": "1",
                "ds_average": "1",
                "ds_total": "0",
                "ds_tickness": 1,
                "ds_color_line_mode": "1",
                "ds_color_line": "#9966ff"
            },
            "legend": "connection_fit",
            "stack": 0,
            "warn": null,
            "warn_low": null,
            "crit": null,
            "crit_low": null,
            "ds_color_area_warn": "#ff9a13",
            "ds_color_area_crit": "#e00b3d",
            "ds_order": 0,
            "data": [
                132.01466667,
                131.8625,
                131.736,
                131.70216667,
                131.7,
                131.7,
                131.71566667,
                131.72783333,
                131.73783333,
                131.74783333,
                131.75783333,
                131.74433333,
                131.6225,
                131.46466667,
                131.36733333,
                131.47533333,
                131.63533333,
                131.77183333,
                131.80783333,
                131.82566667,
                131.83783333,
                131.84783333,
                131.85783333,
                131.8365,
                131.7125,
                131.5625,
                131.21666667,
                130.143,
                128.883,
                122.453,
                95.894833333,
                64.157,
                37.156166667,
                28.574166667,
                24.724166667,
                21.500833333,
                20.714666667,
                20.5625,
                20.420333333,
                20.327333333,
                20.247333333,
                20.245666667,
                20.516333333,
                20.856333333,
                21.031833333,
                20.574333333,
                19.962166667,
                19.446166667,
                19.34,
                19.34,
                19.379166667,
                19.570166667,
                19.792333333,
                19.949666667,
                19.878166667,
                19.740333333,
                19.631666667,
                19.625666667,
                19.645666667,
                19.681333333,
                19.784,
                19.896166667,
                19.967,
                19.870333333,
                19.738166667,
                19.631666667,
                19.617833333,
                19.627833333,
                19.645666667,
                19.689166667,
                19.739166667,
                19.781333333,
                19.782166667,
                19.772166667,
                19.7465,
                19.646,
                19.518166667,
                19.411666667,
                19.397833333,
                19.415666667,
                19.435666667,
                19.479166667,
                19.529166667,
                19.5635,
                19.57,
                19.562166667,
                19.544333333,
                19.477333333,
                19.405166667,
                19.350833333,
                19.347833333,
                19.357833333,
                19.375666667,
                19.419166667,
                19.469166667,
                19.511333333,
                19.512166667,
                19.51,
                19.502166667,
                19.492166667,
                19.49,
                19.49,
                19.5135,
                19.535666667,
                19.5635,
                19.609166667,
                19.659166667,
                19.701333333,
                19.702166667,
                19.692166667,
                19.69,
                19.7135,
                19.751333333,
                19.7835,
                19.805666667,
                19.825666667,
                19.861333333,
                19.932666667,
                20.012666667,
                20.084833333,
                20.107833333,
                20.11,
                20.117833333,
                20.112166667,
                20.102166667,
                20.1235,
                20.224,
                20.351833333,
                20.427,
                20.306833333,
                20.144666667,
                20.008166667,
                20.011333333,
                20.0435,
                20.081333333,
                20.176166667,
                20.286166667,
                20.388333333,
                20.449166667,
                20.491333333,
                20.507833333,
                20.408166667,
                20.278166667,
                20.171666667,
                20.1735,
                20.2035,
                20.241333333,
                20.312666667,
                20.392666667,
                20.464833333,
                20.511333333,
                20.559166667,
                20.577833333,
                20.486,
                20.366,
                20.2695,
                20.2735,
                20.3035,
                20.349166667,
                20.4305,
                20.5205,
                20.602666667,
                20.6435,
                20.681333333,
                20.682166667,
                20.554666667,
                20.394666667,
                20.273833333,
                20.2735,
                20.3035,
                20.349166667,
                20.4775,
                20.6275,
                20.754,
                20.8035,
                20.841333333,
                20.842166667,
                20.714666667,
                20.554666667,
                20.433833333,
                20.4335,
                20.4635,
                20.485666667,
                20.435166667,
                20.373,
                20.328666667,
                20.3435,
                20.381333333,
                20.382166667,
                20.254666667,
                20.094666667,
                19.966,
                19.971333333,
                20.0035,
                20.049166667,
                20.146166667,
                20.248333333,
                20.348333333,
                20.3935,
                20.4235,
                20.437833333,
                20.353833333,
                20.243833333,
                20.157333333,
                20.171333333,
                20.2035,
                20.272666667,
                20.478,
                20.718,
                27.169833333,
                57.798,
                93.035333333,
                123.62416667,
                136.02416667,
                140.57416667,
                144.22583333,
                145.98166667,
                146.8475,
                146.90083333,
                145.2275,
                142.74333333,
                140.03583333,
                136.845,
                133.425,
                130.66416667,
                129.29,
                128.57,
                127.9025,
                127.33666667,
                126.81083333,
                127.03333333,
                128.83166667,
                131.3775,
                133.3325,
                134.04583333,
                134.17,
                134.09166667,
                133.5975,
                132.90166667,
                132.24833333,
                131.68666667,
                131.16666667,
                131.1075,
                132.03666667,
                133.43083333,
                134.51166667,
                134.93416667,
                135.04416667,
                134.95583333,
                134.4575,
                133.76166667,
                133.10833333,
                132.54666667,
                132.02666667,
                131.8975,
                132.6075,
                133.7175,
                134.5825,
                134.93416667,
                135.04416667,
                134.95583333,
                134.4575,
                133.76166667,
                133.10833333,
                132.54666667,
                132.02666667,
                131.80416667,
                132.22,
                132.94,
                133.51416667,
                133.77416667,
                133.87833333,
                133.79166667,
                133.29166667,
                132.5975,
                131.94833333,
                131.38666667,
                130.86083333,
                130.59333333,
                130.86916667,
                131.405,
                131.8575,
                132.13083333,
                132.32083333,
                132.295,
                131.8175,
                131.12166667,
                null,
                null
            ],
            "prints": [
                [
                    "Last:131.12"
                ],
                [
                    "Min:19.34"
                ],
                [
                    "Max:146.90"
                ],
                [
                    "Average:62.29"
                ]
            ],
            "last_value": 131.12,
            "minimum_value": 19.34,
            "maximum_value": 146.9,
            "average_value": 62.29
        },
        {
            "index_id": 152034,
            "metric_id": 16203,
            "metric": "connection_lower_margin",
            "metric_legend": "connection_lower_margin",
            "unit": "",
            "hidden": 0,
            "min": null,
            "max": null,
            "virtual": 0,
            "ds_data": {
                "ds_min": "1",
                "ds_max": "1",
                "ds_minmax_int": "0",
                "ds_last": "1",
                "ds_average": "1",
                "ds_total": "0",
                "ds_tickness": 1,
                "ds_color_line_mode": "1",
                "ds_color_line": "#000033"
            },
            "legend": "connection_lower_margin",
            "stack": 0,
            "warn": null,
            "warn_low": null,
            "crit": null,
            "crit_low": null,
            "ds_color_area_warn": "#ff9a13",
            "ds_color_area_crit": "#e00b3d",
            "ds_order": 0,
            "data": [
                -95.2,
                -95.2,
                -95.2,
                -95.2,
                -95.2,
                -95.2,
                -95.2,
                -95.2,
                -95.2,
                -95.2,
                -95.2,
                -95.2,
                -95.2,
                -95.2,
                -95.2,
                -95.2,
                -95.2,
                -95.2,
                -95.2,
                -95.2,
                -95.2,
                -95.2,
                -95.2,
                -95.2,
                -95.2,
                -95.2,
                -95.2,
                -95.2,
                -95.2,
                -90.789833333,
                -69.1955,
                -43.193333333,
                -21.595666667,
                -17.18,
                -17.18,
                -17.18,
                -17.18,
                -17.18,
                -17.18,
                -17.18,
                -17.18,
                -17.18,
                -17.18,
                -17.18,
                -17.18,
                -17.18,
                -17.18,
                -17.18,
                -17.18,
                -17.18,
                -17.18,
                -17.18,
                -17.18,
                -17.18,
                -17.18,
                -17.18,
                -17.18,
                -17.18,
                -17.18,
                -17.18,
                -17.18,
                -17.18,
                -17.18,
                -17.18,
                -17.18,
                -17.18,
                -17.18,
                -17.18,
                -17.18,
                -17.18,
                -17.18,
                -17.18,
                -17.18,
                -17.18,
                -17.18,
                -17.18,
                -17.18,
                -17.18,
                -17.18,
                -17.18,
                -17.18,
                -17.18,
                -17.18,
                -17.18,
                -17.18,
                -17.18,
                -17.18,
                -17.18,
                -17.18,
                -17.18,
                -17.18,
                -17.18,
                -17.18,
                -17.18,
                -17.18,
                -17.18,
                -17.18,
                -17.18,
                -17.18,
                -17.18,
                -17.18,
                -17.18,
                -17.18,
                -17.18,
                -17.18,
                -17.18,
                -17.18,
                -17.18,
                -17.18,
                -17.18,
                -17.18,
                -17.18,
                -17.18,
                -17.18,
                -17.18,
                -17.18,
                -17.18,
                -17.18,
                -17.18,
                -17.18,
                -17.18,
                -17.18,
                -17.18,
                -17.18,
                -17.18,
                -17.18,
                -17.18,
                -17.18,
                -17.18,
                -17.18,
                -17.18,
                -17.18,
                -17.18,
                -17.18,
                -17.18,
                -17.18,
                -17.18,
                -17.18,
                -17.18,
                -17.18,
                -17.18,
                -17.18,
                -17.18,
                -17.18,
                -17.18,
                -17.18,
                -17.18,
                -17.18,
                -17.18,
                -17.18,
                -17.18,
                -17.18,
                -17.18,
                -17.18,
                -17.18,
                -17.18,
                -17.18,
                -17.18,
                -17.18,
                -17.18,
                -17.18,
                -17.18,
                -17.18,
                -17.18,
                -17.18,
                -17.18,
                -17.18,
                -17.18,
                -17.18,
                -17.18,
                -17.18,
                -17.18,
                -17.18,
                -17.18,
                -17.18,
                -17.18,
                -17.18,
                -17.18,
                -17.18,
                -17.18,
                -17.18,
                -17.18,
                -17.18,
                -17.18,
                -17.18,
                -17.18,
                -17.18,
                -17.18,
                -17.18,
                -17.18,
                -17.18,
                -17.18,
                -17.18,
                -17.18,
                -17.18,
                -17.18,
                -17.18,
                -17.18,
                -17.18,
                -17.18,
                -17.18,
                -17.18,
                -17.18,
                -17.18,
                -17.18,
                -17.18,
                -17.18,
                -17.18,
                -17.18,
                -21.598,
                -43.1945,
                -68.07,
                -88.879166667,
                -95.2,
                -95.2,
                -95.2,
                -95.2,
                -95.2,
                -95.2,
                -95.2,
                -95.2,
                -95.2,
                -95.2,
                -95.2,
                -95.2,
                -95.2,
                -95.2,
                -95.2,
                -95.2,
                -95.2,
                -95.2,
                -95.2,
                -95.2,
                -95.2,
                -95.2,
                -95.2,
                -95.2,
                -95.2,
                -95.2,
                -95.2,
                -95.2,
                -95.2,
                -95.2,
                -95.2,
                -95.2,
                -95.2,
                -95.2,
                -95.2,
                -95.2,
                -95.2,
                -95.2,
                -95.2,
                -95.2,
                -95.2,
                -95.2,
                -95.2,
                -95.2,
                -95.2,
                -95.2,
                -95.2,
                -95.2,
                -95.2,
                -95.2,
                -95.2,
                -95.2,
                -95.2,
                -95.2,
                -95.2,
                -95.2,
                -95.2,
                -95.2,
                -95.2,
                -95.2,
                -95.2,
                -95.2,
                -95.2,
                -95.2,
                -95.2,
                -95.2,
                -95.2,
                -95.2,
                -95.2,
                -95.2,
                -95.2,
                -95.2,
                -95.2,
                -95.2,
                null,
                null
            ],
            "prints": [
                [
                    "Last:-95.20"
                ],
                [
                    "Min:-95.20"
                ],
                [
                    "Max:-17.18"
                ],
                [
                    "Average:-46.26"
                ]
            ],
            "last_value": null,
            "minimum_value": null,
            "maximum_value": null,
            "average_value": null
        },
        {
            "index_id": 152034,
            "metric_id": 16204,
            "metric": "connection_upper_margin",
            "metric_legend": "connection_upper_margin",
            "unit": "",
            "hidden": 0,
            "min": null,
            "max": null,
            "virtual": 0,
            "ds_data": {
                "ds_min": "1",
                "ds_max": "1",
                "ds_minmax_int": "0",
                "ds_last": "1",
                "ds_average": "1",
                "ds_total": "0",
                "ds_tickness": 1,
                "ds_color_line_mode": "1",
                "ds_color_line": "#99cc66"
            },
            "legend": "connection_upper_margin",
            "stack": 0,
            "warn": null,
            "warn_low": null,
            "crit": null,
            "crit_low": null,
            "ds_color_area_warn": "#ff9a13",
            "ds_color_area_crit": "#e00b3d",
            "ds_order": 0,
            "data": [
                100.19,
                100.19,
                100.19,
                100.19,
                100.19,
                100.19,
                100.19,
                100.19,
                100.19,
                100.19,
                100.19,
                100.19,
                100.19,
                100.19,
                100.19,
                100.19,
                100.19,
                100.19,
                100.19,
                100.19,
                100.19,
                100.19,
                100.19,
                100.19,
                100.19,
                100.19,
                100.19,
                100.19,
                100.19,
                95.380333333,
                71.858166667,
                43.536,
                20.017833333,
                15.21,
                15.21,
                15.21,
                15.21,
                15.21,
                15.21,
                15.21,
                15.21,
                15.21,
                15.21,
                15.21,
                15.21,
                15.21,
                15.21,
                15.21,
                15.21,
                15.21,
                15.21,
                15.21,
                15.21,
                15.21,
                15.21,
                15.21,
                15.21,
                15.21,
                15.21,
                15.21,
                15.21,
                15.21,
                15.21,
                15.21,
                15.21,
                15.21,
                15.21,
                15.21,
                15.21,
                15.21,
                15.21,
                15.21,
                15.21,
                15.21,
                15.21,
                15.21,
                15.21,
                15.21,
                15.21,
                15.21,
                15.21,
                15.21,
                15.21,
                15.21,
                15.21,
                15.21,
                15.21,
                15.21,
                15.21,
                15.21,
                15.21,
                15.21,
                15.21,
                15.21,
                15.21,
                15.21,
                15.21,
                15.21,
                15.21,
                15.21,
                15.21,
                15.21,
                15.21,
                15.21,
                15.21,
                15.21,
                15.21,
                15.21,
                15.21,
                15.21,
                15.21,
                15.21,
                15.21,
                15.21,
                15.21,
                15.21,
                15.21,
                15.21,
                15.21,
                15.21,
                15.21,
                15.21,
                15.21,
                15.21,
                15.21,
                15.21,
                15.21,
                15.21,
                15.21,
                15.21,
                15.21,
                15.21,
                15.21,
                15.21,
                15.21,
                15.21,
                15.21,
                15.21,
                15.21,
                15.21,
                15.21,
                15.21,
                15.21,
                15.21,
                15.21,
                15.21,
                15.21,
                15.21,
                15.21,
                15.21,
                15.21,
                15.21,
                15.21,
                15.21,
                15.21,
                15.21,
                15.21,
                15.21,
                15.21,
                15.21,
                15.21,
                15.21,
                15.21,
                15.21,
                15.21,
                15.21,
                15.21,
                15.21,
                15.21,
                15.21,
                15.21,
                15.21,
                15.21,
                15.21,
                15.21,
                15.21,
                15.21,
                15.21,
                15.21,
                15.21,
                15.21,
                15.21,
                15.21,
                15.21,
                15.21,
                15.21,
                15.21,
                15.21,
                15.21,
                15.21,
                15.21,
                15.21,
                15.21,
                15.21,
                15.21,
                15.21,
                15.21,
                15.21,
                15.21,
                15.21,
                15.21,
                15.21,
                15.21,
                15.21,
                15.21,
                15.21,
                15.21,
                15.21,
                15.21,
                20.019666667,
                43.534,
                70.6315,
                93.3025,
                100.19,
                100.19,
                100.19,
                100.19,
                100.19,
                100.19,
                100.19,
                100.19,
                100.19,
                100.19,
                100.19,
                100.19,
                100.19,
                100.19,
                100.19,
                100.19,
                100.19,
                100.19,
                100.19,
                100.19,
                100.19,
                100.19,
                100.19,
                100.19,
                100.19,
                100.19,
                100.19,
                100.19,
                100.19,
                100.19,
                100.19,
                100.19,
                100.19,
                100.19,
                100.19,
                100.19,
                100.19,
                100.19,
                100.19,
                100.19,
                100.19,
                100.19,
                100.19,
                100.19,
                100.19,
                100.19,
                100.19,
                100.19,
                100.19,
                100.19,
                100.19,
                100.19,
                100.19,
                100.19,
                100.19,
                100.19,
                100.19,
                100.19,
                100.19,
                100.19,
                100.19,
                100.19,
                100.19,
                100.19,
                100.19,
                100.19,
                100.19,
                100.19,
                100.19,
                100.19,
                100.19,
                100.19,
                100.19,
                100.19,
                null,
                null
            ],
            "prints": [
                [
                    "Last:100.19"
                ],
                [
                    "Min:15.21"
                ],
                [
                    "Max:100.19"
                ],
                [
                    "Average:46.88"
                ]
            ],
            "last_value": 100.19,
            "minimum_value": 15.21,
            "maximum_value": 100.19,
            "average_value": 46.88
        },
        {
            "index_id": 152034,
            "metric_id": 15171,
            "metric": "connection_lower_thresholds",
            "metric_legend": "connection_lower_thresholds",
            "unit": "",
            "hidden": 0,
            "min": null,
            "max": null,
            "virtual": 0,
            "ds_data": {
                "compo_id": 50,
                "host_id": null,
                "service_id": null,
                "name": "Anomaly Lower Threshold",
                "ds_order": 1,
                "ds_hidecurve": null,
                "ds_name": ".*_lower_thresholds",
                "ds_color_line": "#D728C9",
                "ds_color_line_mode": "0",
                "ds_color_area": "#FFFFFF",
                "ds_color_area_warn": "#F8C706",
                "ds_color_area_crit": "#F91E05",
                "ds_filled": null,
                "ds_max": null,
                "ds_min": null,
                "ds_minmax_int": null,
                "ds_average": null,
                "ds_last": null,
                "ds_total": null,
                "ds_tickness": 2,
                "ds_transparency": "80",
                "ds_invert": null,
                "ds_legend": "Lower Threshold",
                "ds_jumpline": "0",
                "ds_stack": null,
                "default_tpl1": null,
                "comment": null
            },
            "legend": "Lower Threshold",
            "stack": 0,
            "warn": null,
            "warn_low": null,
            "crit": null,
            "crit_low": null,
            "ds_order": 1,
            "data": [
                -10.7875,
                -10.9375,
                -11.071833333,
                -11.1,
                -11.1,
                -11.1,
                -11.092166667,
                -11.074333333,
                -11.062166667,
                -11.052166667,
                -11.042166667,
                -11.0635,
                -11.1875,
                -11.3375,
                -11.4405,
                -11.334666667,
                -11.174666667,
                -11.038166667,
                -10.994333333,
                -10.982166667,
                -10.972166667,
                -10.962166667,
                -10.944333333,
                -10.9635,
                -11.0875,
                -11.245333333,
                -11.5855,
                -12.657,
                -13.917,
                -13.727833333,
                -7.9051666667,
                -0.62733333333,
                4.757,
                2.7941666667,
                -1.0558333333,
                -4.2791666667,
                -5.0575,
                -5.2153333333,
                -5.3518333333,
                -5.4426666667,
                -5.5226666667,
                -5.5321666667,
                -5.2636666667,
                -4.9236666667,
                -4.7481666667,
                -5.1978333333,
                -5.8156666667,
                -6.326,
                -6.43,
                -6.43,
                -6.3908333333,
                -6.2076666667,
                -5.9876666667,
                -5.8225,
                -5.8996666667,
                -6.0318333333,
                -6.1383333333,
                -6.1443333333,
                -6.1243333333,
                -6.0886666667,
                -5.9938333333,
                -5.8838333333,
                -5.813,
                -5.9018333333,
                -6.0396666667,
                -6.1483333333,
                -6.1621666667,
                -6.1443333333,
                -6.1243333333,
                -6.0808333333,
                -6.0308333333,
                -5.9965,
                -5.99,
                -5.9978333333,
                -6.0235,
                -6.1318333333,
                -6.2618333333,
                -6.3605,
                -6.3721666667,
                -6.3621666667,
                -6.3443333333,
                -6.3008333333,
                -6.2508333333,
                -6.2086666667,
                -6.2078333333,
                -6.2178333333,
                -6.2356666667,
                -6.2948333333,
                -6.3648333333,
                -6.427,
                -6.4321666667,
                -6.4143333333,
                -6.3943333333,
                -6.3508333333,
                -6.3008333333,
                -6.2665,
                -6.26,
                -6.2678333333,
                -6.2778333333,
                -6.28,
                -6.2878333333,
                -6.2821666667,
                -6.2643333333,
                -6.2443333333,
                -6.2165,
                -6.1708333333,
                -6.1208333333,
                -6.0786666667,
                -6.0778333333,
                -6.0878333333,
                -6.09,
                -6.0586666667,
                -6.0265,
                -5.9965,
                -5.9743333333,
                -5.9465,
                -5.9165,
                -5.8473333333,
                -5.7673333333,
                -5.6951666667,
                -5.6721666667,
                -5.6621666667,
                -5.66,
                -5.66,
                -5.6678333333,
                -5.6543333333,
                -5.5481666667,
                -5.426,
                -5.353,
                -5.4653333333,
                -5.6331666667,
                -5.764,
                -5.7665,
                -5.7365,
                -5.6908333333,
                -5.5938333333,
                -5.4838333333,
                -5.3895,
                -5.3308333333,
                -5.2808333333,
                -5.27,
                -5.3718333333,
                -5.5018333333,
                -5.6083333333,
                -5.5986666667,
                -5.5665,
                -5.5286666667,
                -5.4651666667,
                -5.3873333333,
                -5.3151666667,
                -5.2608333333,
                -5.2186666667,
                -5.2021666667,
                -5.294,
                -5.414,
                -5.5105,
                -5.5065,
                -5.4765,
                -5.4308333333,
                -5.3495,
                -5.2595,
                -5.1773333333,
                -5.1286666667,
                -5.0965,
                -5.0978333333,
                -5.2175,
                -5.3753333333,
                -5.504,
                -5.5065,
                -5.4765,
                -5.423,
                -5.3003333333,
                -5.1525,
                -5.026,
                -4.9686666667,
                -4.9365,
                -4.9378333333,
                -5.0575,
                -5.2153333333,
                -5.344,
                -5.3465,
                -5.3086666667,
                -5.2921666667,
                -5.337,
                -5.4048333333,
                -5.4513333333,
                -5.4286666667,
                -5.3965,
                -5.3978333333,
                -5.5253333333,
                -5.6775,
                -5.804,
                -5.8065,
                -5.7686666667,
                -5.7286666667,
                -5.6338333333,
                -5.5238333333,
                -5.4295,
                -5.3865,
                -5.3486666667,
                -5.34,
                -5.4261666667,
                -5.5361666667,
                -5.6148333333,
                -5.6065,
                -5.5765,
                -5.5073333333,
                -5.302,
                -5.062,
                -5.2293333333,
                -6.9898333333,
                -9.0705,
                -9.7025,
                -6.7858333333,
                -2.2358333333,
                1.4216666667,
                3.1816666667,
                4.0416666667,
                4.0908333333,
                2.4233333333,
                -0.056666666667,
                -2.77,
                -5.965,
                -9.385,
                -12.145833333,
                -13.514166667,
                -14.23,
                -14.903333333,
                -15.473333333,
                -15.993333333,
                -15.766666667,
                -13.968333333,
                -11.428333333,
                -9.4716666667,
                -8.76,
                -8.6341666667,
                -8.7083333333,
                -9.2083333333,
                -9.9025,
                -10.551666667,
                -11.113333333,
                -11.639166667,
                -11.696666667,
                -10.769166667,
                -9.3733333333,
                -8.2883333333,
                -7.8716666667,
                -7.7658333333,
                -7.8483333333,
                -8.3483333333,
                -9.0425,
                -9.6975,
                -10.263333333,
                -10.783333333,
                -10.906666667,
                -10.1925,
                -9.0883333333,
                -8.2216666667,
                -7.8716666667,
                -7.7658333333,
                -7.8483333333,
                -8.3483333333,
                -9.0425,
                -9.6975,
                -10.263333333,
                -10.783333333,
                -11,
                -10.58,
                -9.86,
                -9.2916666667,
                -9.0358333333,
                -8.9258333333,
                -9.0141666667,
                -9.5125,
                -10.2025,
                -10.8575,
                -11.423333333,
                -11.943333333,
                -12.206666667,
                -11.930833333,
                -11.400833333,
                -10.9525,
                -10.679166667,
                -10.483333333,
                -10.505,
                -10.988333333,
                -11.6825,
                null,
                null
            ],
            "prints": [],
            "last_value": null,
            "minimum_value": null,
            "maximum_value": null,
            "average_value": null
        },
        {
            "index_id": 152034,
            "metric_id": 15172,
            "metric": "connection_upper_thresholds",
            "metric_legend": "connection_upper_thresholds",
            "unit": "",
            "hidden": 0,
            "min": null,
            "max": null,
            "virtual": 0,
            "ds_data": {
                "compo_id": 51,
                "host_id": null,
                "service_id": null,
                "name": "Anomaly Upper Threshold",
                "ds_order": 1,
                "ds_hidecurve": null,
                "ds_name": ".*_upper_thresholds",
                "ds_color_line": "#D728C9",
                "ds_color_line_mode": "0",
                "ds_color_area": "#FFFFFF",
                "ds_color_area_warn": "#F8C706",
                "ds_color_area_crit": "#F91E05",
                "ds_filled": null,
                "ds_max": null,
                "ds_min": null,
                "ds_minmax_int": null,
                "ds_average": null,
                "ds_last": null,
                "ds_total": null,
                "ds_tickness": 2,
                "ds_transparency": "80",
                "ds_invert": null,
                "ds_legend": "Upper Threshold",
                "ds_jumpline": "0",
                "ds_stack": null,
                "default_tpl1": null,
                "comment": null
            },
            "legend": "Upper Threshold",
            "stack": 0,
            "warn": null,
            "warn_low": null,
            "crit": null,
            "crit_low": null,
            "ds_order": 1,
            "data": [
                282.29466667,
                282.1425,
                282.016,
                281.98216667,
                281.98,
                281.98,
                281.98783333,
                282.00566667,
                282.01783333,
                282.02783333,
                282.03783333,
                282.02433333,
                281.89466667,
                281.7425,
                281.64733333,
                281.75533333,
                281.91533333,
                282.044,
                282.08566667,
                282.09783333,
                282.11566667,
                282.12783333,
                282.13783333,
                282.1165,
                281.9925,
                281.8425,
                281.49666667,
                280.423,
                279.163,
                265.52633333,
                203.68316667,
                129.461,
                67.179,
                51.384166667,
                47.534166667,
                44.310833333,
                43.5325,
                43.374666667,
                43.230333333,
                43.145166667,
                43.067333333,
                43.057833333,
                43.326333333,
                43.666333333,
                43.841833333,
                43.392166667,
                42.774333333,
                42.264,
                42.16,
                42.16,
                42.199166667,
                42.382333333,
                42.602333333,
                42.7675,
                42.690333333,
                42.558166667,
                42.443833333,
                42.435666667,
                42.4635,
                42.501333333,
                42.596166667,
                42.706166667,
                42.777,
                42.688166667,
                42.550333333,
                42.441666667,
                42.427833333,
                42.445666667,
                42.465666667,
                42.509166667,
                42.559166667,
                42.5935,
                42.6,
                42.592166667,
                42.558666667,
                42.456,
                42.328166667,
                42.221666667,
                42.215666667,
                42.227833333,
                42.245666667,
                42.289166667,
                42.339166667,
                42.381333333,
                42.382166667,
                42.372166667,
                42.354333333,
                42.295166667,
                42.225166667,
                42.163,
                42.157833333,
                42.175666667,
                42.195666667,
                42.239166667,
                42.289166667,
                42.3235,
                42.33,
                42.322166667,
                42.312166667,
                42.31,
                42.302166667,
                42.307833333,
                42.325666667,
                42.345666667,
                42.3735,
                42.419166667,
                42.469166667,
                42.511333333,
                42.512166667,
                42.502166667,
                42.5,
                42.531333333,
                42.5635,
                42.5935,
                42.615666667,
                42.635666667,
                42.671333333,
                42.742666667,
                42.822666667,
                42.894833333,
                42.917833333,
                42.927833333,
                42.93,
                42.93,
                42.922166667,
                42.935666667,
                43.034,
                43.161833333,
                43.237,
                43.124666667,
                42.956833333,
                42.826,
                42.8235,
                42.8535,
                42.899166667,
                42.996166667,
                43.106166667,
                43.2005,
                43.259166667,
                43.309166667,
                43.32,
                43.218166667,
                43.088166667,
                42.981666667,
                42.9835,
                43.021333333,
                43.061333333,
                43.124833333,
                43.202666667,
                43.274833333,
                43.329166667,
                43.371333333,
                43.387833333,
                43.296,
                43.176,
                43.0795,
                43.0835,
                43.1135,
                43.159166667,
                43.2405,
                43.3305,
                43.412666667,
                43.461333333,
                43.4935,
                43.492166667,
                43.364666667,
                43.2125,
                43.086,
                43.0835,
                43.1135,
                43.167,
                43.289666667,
                43.4375,
                43.564,
                43.621333333,
                43.6535,
                43.652166667,
                43.524666667,
                43.3725,
                43.246,
                43.2435,
                43.281333333,
                43.297833333,
                43.253,
                43.185166667,
                43.138666667,
                43.161333333,
                43.1935,
                43.192166667,
                43.064666667,
                42.904666667,
                42.783833333,
                42.7835,
                42.8135,
                42.859166667,
                42.956166667,
                43.066166667,
                43.1605,
                43.2035,
                43.241333333,
                43.25,
                43.163833333,
                43.053833333,
                42.967333333,
                42.981333333,
                43.0135,
                43.082666667,
                43.288,
                43.528,
                57.194333333,
                123.094,
                198.9815,
                263.56916667,
                286.29416667,
                290.85,
                294.50583333,
                296.26166667,
                297.1275,
                297.18083333,
                295.5075,
                293.02333333,
                290.31583333,
                287.125,
                283.705,
                280.94416667,
                279.57,
                278.85,
                278.1825,
                277.61666667,
                277.09083333,
                277.31333333,
                279.11166667,
                281.6575,
                283.6125,
                284.32583333,
                284.45,
                284.37166667,
                283.8775,
                283.18166667,
                282.52833333,
                281.96666667,
                281.44666667,
                281.3875,
                282.31666667,
                283.71083333,
                284.79166667,
                285.21416667,
                285.32416667,
                285.23583333,
                284.7375,
                284.04166667,
                283.38833333,
                282.82666667,
                282.30083333,
                282.17333333,
                282.8875,
                283.9975,
                284.8625,
                285.21416667,
                285.32416667,
                285.23583333,
                284.7375,
                284.04166667,
                283.38833333,
                282.82666667,
                282.30083333,
                282.08,
                282.5,
                283.22,
                283.79416667,
                284.05416667,
                284.15833333,
                284.07166667,
                283.57166667,
                282.8775,
                282.22833333,
                281.66083333,
                281.13666667,
                280.87333333,
                281.14916667,
                281.685,
                282.1375,
                282.41083333,
                282.60083333,
                282.575,
                282.0975,
                281.40166667,
                null,
                null
            ],
            "prints": [],
            "last_value": null,
            "minimum_value": null,
            "maximum_value": null,
            "average_value": null
        }
    ],
    "times": [
        "2023-06-04T15:35:00+02:00",
        "2023-06-04T15:40:00+02:00",
        "2023-06-04T15:45:00+02:00",
        "2023-06-04T15:50:00+02:00",
        "2023-06-04T15:55:00+02:00",
        "2023-06-04T16:00:00+02:00",
        "2023-06-04T16:05:00+02:00",
        "2023-06-04T16:10:00+02:00",
        "2023-06-04T16:15:00+02:00",
        "2023-06-04T16:20:00+02:00",
        "2023-06-04T16:25:00+02:00",
        "2023-06-04T16:30:00+02:00",
        "2023-06-04T16:35:00+02:00",
        "2023-06-04T16:40:00+02:00",
        "2023-06-04T16:45:00+02:00",
        "2023-06-04T16:50:00+02:00",
        "2023-06-04T16:55:00+02:00",
        "2023-06-04T17:00:00+02:00",
        "2023-06-04T17:05:00+02:00",
        "2023-06-04T17:10:00+02:00",
        "2023-06-04T17:15:00+02:00",
        "2023-06-04T17:20:00+02:00",
        "2023-06-04T17:25:00+02:00",
        "2023-06-04T17:30:00+02:00",
        "2023-06-04T17:35:00+02:00",
        "2023-06-04T17:40:00+02:00",
        "2023-06-04T17:45:00+02:00",
        "2023-06-04T17:50:00+02:00",
        "2023-06-04T17:55:00+02:00",
        "2023-06-04T18:00:00+02:00",
        "2023-06-04T18:05:00+02:00",
        "2023-06-04T18:10:00+02:00",
        "2023-06-04T18:15:00+02:00",
        "2023-06-04T18:20:00+02:00",
        "2023-06-04T18:25:00+02:00",
        "2023-06-04T18:30:00+02:00",
        "2023-06-04T18:35:00+02:00",
        "2023-06-04T18:40:00+02:00",
        "2023-06-04T18:45:00+02:00",
        "2023-06-04T18:50:00+02:00",
        "2023-06-04T18:55:00+02:00",
        "2023-06-04T19:00:00+02:00",
        "2023-06-04T19:05:00+02:00",
        "2023-06-04T19:10:00+02:00",
        "2023-06-04T19:15:00+02:00",
        "2023-06-04T19:20:00+02:00",
        "2023-06-04T19:25:00+02:00",
        "2023-06-04T19:30:00+02:00",
        "2023-06-04T19:35:00+02:00",
        "2023-06-04T19:40:00+02:00",
        "2023-06-04T19:45:00+02:00",
        "2023-06-04T19:50:00+02:00",
        "2023-06-04T19:55:00+02:00",
        "2023-06-04T20:00:00+02:00",
        "2023-06-04T20:05:00+02:00",
        "2023-06-04T20:10:00+02:00",
        "2023-06-04T20:15:00+02:00",
        "2023-06-04T20:20:00+02:00",
        "2023-06-04T20:25:00+02:00",
        "2023-06-04T20:30:00+02:00",
        "2023-06-04T20:35:00+02:00",
        "2023-06-04T20:40:00+02:00",
        "2023-06-04T20:45:00+02:00",
        "2023-06-04T20:50:00+02:00",
        "2023-06-04T20:55:00+02:00",
        "2023-06-04T21:00:00+02:00",
        "2023-06-04T21:05:00+02:00",
        "2023-06-04T21:10:00+02:00",
        "2023-06-04T21:15:00+02:00",
        "2023-06-04T21:20:00+02:00",
        "2023-06-04T21:25:00+02:00",
        "2023-06-04T21:30:00+02:00",
        "2023-06-04T21:35:00+02:00",
        "2023-06-04T21:40:00+02:00",
        "2023-06-04T21:45:00+02:00",
        "2023-06-04T21:50:00+02:00",
        "2023-06-04T21:55:00+02:00",
        "2023-06-04T22:00:00+02:00",
        "2023-06-04T22:05:00+02:00",
        "2023-06-04T22:10:00+02:00",
        "2023-06-04T22:15:00+02:00",
        "2023-06-04T22:20:00+02:00",
        "2023-06-04T22:25:00+02:00",
        "2023-06-04T22:30:00+02:00",
        "2023-06-04T22:35:00+02:00",
        "2023-06-04T22:40:00+02:00",
        "2023-06-04T22:45:00+02:00",
        "2023-06-04T22:50:00+02:00",
        "2023-06-04T22:55:00+02:00",
        "2023-06-04T23:00:00+02:00",
        "2023-06-04T23:05:00+02:00",
        "2023-06-04T23:10:00+02:00",
        "2023-06-04T23:15:00+02:00",
        "2023-06-04T23:20:00+02:00",
        "2023-06-04T23:25:00+02:00",
        "2023-06-04T23:30:00+02:00",
        "2023-06-04T23:35:00+02:00",
        "2023-06-04T23:40:00+02:00",
        "2023-06-04T23:45:00+02:00",
        "2023-06-04T23:50:00+02:00",
        "2023-06-04T23:55:00+02:00",
        "2023-06-05T00:00:00+02:00",
        "2023-06-05T00:05:00+02:00",
        "2023-06-05T00:10:00+02:00",
        "2023-06-05T00:15:00+02:00",
        "2023-06-05T00:20:00+02:00",
        "2023-06-05T00:25:00+02:00",
        "2023-06-05T00:30:00+02:00",
        "2023-06-05T00:35:00+02:00",
        "2023-06-05T00:40:00+02:00",
        "2023-06-05T00:45:00+02:00",
        "2023-06-05T00:50:00+02:00",
        "2023-06-05T00:55:00+02:00",
        "2023-06-05T01:00:00+02:00",
        "2023-06-05T01:05:00+02:00",
        "2023-06-05T01:10:00+02:00",
        "2023-06-05T01:15:00+02:00",
        "2023-06-05T01:20:00+02:00",
        "2023-06-05T01:25:00+02:00",
        "2023-06-05T01:30:00+02:00",
        "2023-06-05T01:35:00+02:00",
        "2023-06-05T01:40:00+02:00",
        "2023-06-05T01:45:00+02:00",
        "2023-06-05T01:50:00+02:00",
        "2023-06-05T01:55:00+02:00",
        "2023-06-05T02:00:00+02:00",
        "2023-06-05T02:05:00+02:00",
        "2023-06-05T02:10:00+02:00",
        "2023-06-05T02:15:00+02:00",
        "2023-06-05T02:20:00+02:00",
        "2023-06-05T02:25:00+02:00",
        "2023-06-05T02:30:00+02:00",
        "2023-06-05T02:35:00+02:00",
        "2023-06-05T02:40:00+02:00",
        "2023-06-05T02:45:00+02:00",
        "2023-06-05T02:50:00+02:00",
        "2023-06-05T02:55:00+02:00",
        "2023-06-05T03:00:00+02:00",
        "2023-06-05T03:05:00+02:00",
        "2023-06-05T03:10:00+02:00",
        "2023-06-05T03:15:00+02:00",
        "2023-06-05T03:20:00+02:00",
        "2023-06-05T03:25:00+02:00",
        "2023-06-05T03:30:00+02:00",
        "2023-06-05T03:35:00+02:00",
        "2023-06-05T03:40:00+02:00",
        "2023-06-05T03:45:00+02:00",
        "2023-06-05T03:50:00+02:00",
        "2023-06-05T03:55:00+02:00",
        "2023-06-05T04:00:00+02:00",
        "2023-06-05T04:05:00+02:00",
        "2023-06-05T04:10:00+02:00",
        "2023-06-05T04:15:00+02:00",
        "2023-06-05T04:20:00+02:00",
        "2023-06-05T04:25:00+02:00",
        "2023-06-05T04:30:00+02:00",
        "2023-06-05T04:35:00+02:00",
        "2023-06-05T04:40:00+02:00",
        "2023-06-05T04:45:00+02:00",
        "2023-06-05T04:50:00+02:00",
        "2023-06-05T04:55:00+02:00",
        "2023-06-05T05:00:00+02:00",
        "2023-06-05T05:05:00+02:00",
        "2023-06-05T05:10:00+02:00",
        "2023-06-05T05:15:00+02:00",
        "2023-06-05T05:20:00+02:00",
        "2023-06-05T05:25:00+02:00",
        "2023-06-05T05:30:00+02:00",
        "2023-06-05T05:35:00+02:00",
        "2023-06-05T05:40:00+02:00",
        "2023-06-05T05:45:00+02:00",
        "2023-06-05T05:50:00+02:00",
        "2023-06-05T05:55:00+02:00",
        "2023-06-05T06:00:00+02:00",
        "2023-06-05T06:05:00+02:00",
        "2023-06-05T06:10:00+02:00",
        "2023-06-05T06:15:00+02:00",
        "2023-06-05T06:20:00+02:00",
        "2023-06-05T06:25:00+02:00",
        "2023-06-05T06:30:00+02:00",
        "2023-06-05T06:35:00+02:00",
        "2023-06-05T06:40:00+02:00",
        "2023-06-05T06:45:00+02:00",
        "2023-06-05T06:50:00+02:00",
        "2023-06-05T06:55:00+02:00",
        "2023-06-05T07:00:00+02:00",
        "2023-06-05T07:05:00+02:00",
        "2023-06-05T07:10:00+02:00",
        "2023-06-05T07:15:00+02:00",
        "2023-06-05T07:20:00+02:00",
        "2023-06-05T07:25:00+02:00",
        "2023-06-05T07:30:00+02:00",
        "2023-06-05T07:35:00+02:00",
        "2023-06-05T07:40:00+02:00",
        "2023-06-05T07:45:00+02:00",
        "2023-06-05T07:50:00+02:00",
        "2023-06-05T07:55:00+02:00",
        "2023-06-05T08:00:00+02:00",
        "2023-06-05T08:05:00+02:00",
        "2023-06-05T08:10:00+02:00",
        "2023-06-05T08:15:00+02:00",
        "2023-06-05T08:20:00+02:00",
        "2023-06-05T08:25:00+02:00",
        "2023-06-05T08:30:00+02:00",
        "2023-06-05T08:35:00+02:00",
        "2023-06-05T08:40:00+02:00",
        "2023-06-05T08:45:00+02:00",
        "2023-06-05T08:50:00+02:00",
        "2023-06-05T08:55:00+02:00",
        "2023-06-05T09:00:00+02:00",
        "2023-06-05T09:05:00+02:00",
        "2023-06-05T09:10:00+02:00",
        "2023-06-05T09:15:00+02:00",
        "2023-06-05T09:20:00+02:00",
        "2023-06-05T09:25:00+02:00",
        "2023-06-05T09:30:00+02:00",
        "2023-06-05T09:35:00+02:00",
        "2023-06-05T09:40:00+02:00",
        "2023-06-05T09:45:00+02:00",
        "2023-06-05T09:50:00+02:00",
        "2023-06-05T09:55:00+02:00",
        "2023-06-05T10:00:00+02:00",
        "2023-06-05T10:05:00+02:00",
        "2023-06-05T10:10:00+02:00",
        "2023-06-05T10:15:00+02:00",
        "2023-06-05T10:20:00+02:00",
        "2023-06-05T10:25:00+02:00",
        "2023-06-05T10:30:00+02:00",
        "2023-06-05T10:35:00+02:00",
        "2023-06-05T10:40:00+02:00",
        "2023-06-05T10:45:00+02:00",
        "2023-06-05T10:50:00+02:00",
        "2023-06-05T10:55:00+02:00",
        "2023-06-05T11:00:00+02:00",
        "2023-06-05T11:05:00+02:00",
        "2023-06-05T11:10:00+02:00",
        "2023-06-05T11:15:00+02:00",
        "2023-06-05T11:20:00+02:00",
        "2023-06-05T11:25:00+02:00",
        "2023-06-05T11:30:00+02:00",
        "2023-06-05T11:35:00+02:00",
        "2023-06-05T11:40:00+02:00",
        "2023-06-05T11:45:00+02:00",
        "2023-06-05T11:50:00+02:00",
        "2023-06-05T11:55:00+02:00",
        "2023-06-05T12:00:00+02:00",
        "2023-06-05T12:05:00+02:00",
        "2023-06-05T12:10:00+02:00",
        "2023-06-05T12:15:00+02:00",
        "2023-06-05T12:20:00+02:00",
        "2023-06-05T12:25:00+02:00",
        "2023-06-05T12:30:00+02:00",
        "2023-06-05T12:35:00+02:00",
        "2023-06-05T12:40:00+02:00",
        "2023-06-05T12:45:00+02:00",
        "2023-06-05T12:50:00+02:00",
        "2023-06-05T12:55:00+02:00",
        "2023-06-05T13:00:00+02:00",
        "2023-06-05T13:05:00+02:00",
        "2023-06-05T13:10:00+02:00",
        "2023-06-05T13:15:00+02:00",
        "2023-06-05T13:20:00+02:00",
        "2023-06-05T13:25:00+02:00",
        "2023-06-05T13:30:00+02:00",
        "2023-06-05T13:35:00+02:00",
        "2023-06-05T13:40:00+02:00",
        "2023-06-05T13:45:00+02:00",
        "2023-06-05T13:50:00+02:00",
        "2023-06-05T13:55:00+02:00",
        "2023-06-05T14:00:00+02:00",
        "2023-06-05T14:05:00+02:00",
        "2023-06-05T14:10:00+02:00",
        "2023-06-05T14:15:00+02:00",
        "2023-06-05T14:20:00+02:00",
        "2023-06-05T14:25:00+02:00",
        "2023-06-05T14:30:00+02:00",
        "2023-06-05T14:35:00+02:00",
        "2023-06-05T14:40:00+02:00",
        "2023-06-05T14:45:00+02:00",
        "2023-06-05T14:50:00+02:00",
        "2023-06-05T14:55:00+02:00",
        "2023-06-05T15:00:00+02:00",
        "2023-06-05T15:05:00+02:00",
        "2023-06-05T15:10:00+02:00",
        "2023-06-05T15:15:00+02:00",
        "2023-06-05T15:20:00+02:00",
        "2023-06-05T15:25:00+02:00",
        "2023-06-05T15:30:00+02:00",
        "2023-06-05T15:35:00+02:00"
    ]
}